gate_api/__init__.py
gate_api/api_client.py
gate_api/configuration.py
gate_api/exceptions.py
gate_api/rest.py
gate_api/api/__init__.py
gate_api/api/account_api.py
gate_api/api/collateral_loan_api.py
gate_api/api/delivery_api.py
gate_api/api/earn_api.py
gate_api/api/earn_uni_api.py
gate_api/api/flash_swap_api.py
gate_api/api/futures_api.py
gate_api/api/margin_api.py
gate_api/api/margin_uni_api.py
gate_api/api/multi_collateral_loan_api.py
gate_api/api/options_api.py
gate_api/api/rebate_api.py
gate_api/api/spot_api.py
gate_api/api/sub_account_api.py
gate_api/api/unified_api.py
gate_api/api/wallet_api.py
gate_api/api/withdrawal_api.py
gate_api/models/__init__.py
gate_api/models/account_balance.py
gate_api/models/account_detail.py
gate_api/models/account_detail_key.py
gate_api/models/account_key_info.py
gate_api/models/account_key_info_perms.py
gate_api/models/account_rate_limit.py
gate_api/models/agency_commission.py
gate_api/models/agency_commission_history.py
gate_api/models/agency_transaction.py
gate_api/models/agency_transaction_history.py
gate_api/models/auto_repay_setting.py
gate_api/models/award_list_struct.py
gate_api/models/award_list_struct_list.py
gate_api/models/batch_amend_item.py
gate_api/models/batch_amend_order_req.py
gate_api/models/batch_futures_order.py
gate_api/models/batch_order.py
gate_api/models/borrow_currency_info.py
gate_api/models/broker_commission.py
gate_api/models/broker_commission1.py
gate_api/models/broker_commission_sub_broker_info.py
gate_api/models/broker_transaction.py
gate_api/models/broker_transaction1.py
gate_api/models/cancel_batch_order.py
gate_api/models/cancel_order_result.py
gate_api/models/collateral_adjust.py
gate_api/models/collateral_adjust_res.py
gate_api/models/collateral_align.py
gate_api/models/collateral_currency.py
gate_api/models/collateral_currency_info.py
gate_api/models/collateral_currency_res.py
gate_api/models/collateral_current_rate.py
gate_api/models/collateral_fix_rate.py
gate_api-7.2.8.dist-info/METADATA
gate_api-7.2.8.dist-info/WHEEL
gate_api-7.2.8.dist-info/top_level.txt
gate_api-7.2.8.dist-info/RECORD
