Metadata-Version: 2.4
Name: gate-api
Version: 7.2.8
Summary: Gate API
Home-page: https://github.com/gate/gateapi-python
Author: Gate API support
Author-email: support@mail.gate.com
Maintainer: gate
Maintainer-email: dev@mail.gate.com
License: Apache License 2.0
Keywords: OpenAPI,OpenAPI-Generator,Gate API
Classifier: License :: OSI Approved :: Apache Software License
Classifier: Programming Language :: Python :: 2
Classifier: Programming Language :: Python :: 2.7
Classifier: Programming Language :: Python :: 3
Requires-Dist: urllib3>=1.15
Requires-Dist: six>=1.10
Requires-Dist: certifi
Requires-Dist: python-dateutil
Dynamic: author
Dynamic: author-email
Dynamic: home-page
Dynamic: keywords
Dynamic: license
Dynamic: requires-dist
Dynamic: summary
